LICENSE
README.md
setup.py
seabornai/__init__.py
seabornai/seabornai.py
seabornai.egg-info/PKG-INFO
seabornai.egg-info/SOURCES.txt
seabornai.egg-info/dependency_links.txt
seabornai.egg-info/requires.txt
seabornai.egg-info/top_level.txt