Metadata-Version: 2.1
Name: seabornai
Version: 0.0.1
Summary: seabornai is a Python library that leverages the OpenAI ChatGPT API to generate Seaborn graphs based on supplied data and prompts/questions.
Home-page: https://github.com/aditya0072001/seabornai
Author: Tripathi Aditya Prakash
Project-URL: Download Statistics, https://pepy.tech/project/seabornai/month
Classifier: Programming Language :: Python :: 3
Classifier: License :: OSI Approved :: MIT License
Classifier: Operating System :: OS Independent
Requires-Python: >=3.6
License-File: LICENSE
